{
    "&testest": {
        "_useDefaultNextButton": true,
        "_nextPageConditions": [],
        "_helpTexts": {},
        "components": {
            "ProgressBar#test": {}
        }
    },
    "&access_code_input": {
        "_useDefaultNextButton": true,
        "_nextPageConditions": [
            "input-not-empty"
        ],
        "_helpTexts": {},
        "components": {
            "TextArea#top": {
                "text": "TEMPLATE_TEXT",
                "_styles": "mt-32"
            },
            "InputField#access-code": {
                "placeholder": "TEMPLATE_PLACEHOLDER",
                "type": "text",
                "_styles": "w-52 mx-auto"
            }
        }
    },
    "&one_pic_intro_page": {
        "_useDefaultNextButton": true,
        "_nextPageConditions": [],
        "_helpTexts": {},
        "components": {
            "TextArea#top": {
                "text": "TEMPLATE_TEXT",
                "_styles": ""
            },
            "TextArea#pic-header": {
                "text": "TEMPLATE_TEXT",
                "_styles": ""
            },
            "Picture#stimulus1": {
                "src": {
                    "path_key": "assets",
                    "filename": "logo.png"
                }
            },
            "ProgressBar#practice": {}
        }
    },
    "&two_pic_intro_page": {
        "_useDefaultNextButton": true,
        "_nextPageConditions": [],
        "_helpTexts": {},
        "components": {
            "TextArea#top": {
                "text": "TEMPLATE_TEXT",
                "_styles": ""
            },
            "TextArea#top-description": {
                "text": "TEMPLATE_TEXT",
                "_styles": "text-left"
            },
            "Horizontal#image-text": {
                "Picture#image-1": {
                    "_styles": "",
                    "src": {
                        "path_key": "assets",
                        "filename": "logo.png"
                    }
                },
                "TextArea#pic-description": {
                    "text": "TEMPLATE_TEXT",
                    "_styles": "m-auto ml-12"
                }
            },
            "Horizontal#image-text-2": {
                "Picture#image-2": {
                    "_styles": "",
                    "src": {
                        "path_key": "assets",
                        "filename": "logo.png"
                    }
                },
                "TextArea#pic-description-2": {
                    "text": "TEMPLATE_TEfXT",
                    "_styles": "m-auto ml-12"
                }
            }
        }
    },
    "&one_pic_with_slider": {
        "_useDefaultNextButton": true,
        "_nextPageConditions": [
            "slider-total"
        ],
        "_helpTexts": {},
        "components": {
            "TextArea#top": {
                "text": "TEXT_2"
            },
            "Horizontal#stimulus-slider": {
                "Vertical#pic-helper": {
                    "TextArea#pic-header": {
                        "text": "TEXT_3",
                        "_styles": ""
                    },
                    "Picture#stimulus1": {
                        "src": {
                            "path_key": "assests",
                            "filename": "logo.png"
                        }
                    }
                },
                "SliderMenu#tutorial": {
                    "_styles": "m-20",
                    "validTotalScore": 10,
                    "sliderBoxWidth": "400px",
                    "defaultSettings": {},
                    "sliders": [
                        {
                            "id": 1,
                            "color": "green",
                            "score": 0,
                            "min": 0,
                            "max": 10
                        }
                    ]
                }
            }
        }
    },
    "&two_pics_with_slider": {
        "_useDefaultNextButton": true,
        "_nextPageConditions": [
            "slider-total"
        ],
        "_helpTexts": {},
        "components": {
            "TextArea#top": {
                "text": "TEMPLATE_TEXT"
            },
            "Horizontal#two-image-slider": {
                "Vertical#pic-helper": {
                    "Picture#image-1": {
                        "src": {
                            "path_key": "assets",
                            "filename": "logo.png"
                        }
                    },
                    "TextArea#pic-description": {
                        "text": "TEMPLATE_TEXT",
                        "_styles": ""
                    }
                },
                "Vertical#pic-helper-2": {
                    "Picture#image-2": {
                        "src": {
                            "path_key": "assets",
                            "filename": "logo.png"
                        }
                    },
                    "TextArea#pic-description-2": {
                        "text": "TEMPLATE_TEXT",
                        "_styles": ""
                    }
                },
                "Vertical#pic-helper-3": {
                    "SliderMenu#tutorial": {
                        "_styles": "",
                        "validTotalScore": 10,
                        "sliderBoxWidth": "400px",
                        "defaultSettings": {},
                        "sliders": [
                            {
                                "id": 1,
                                "color": "green",
                                "score": 0,
                                "min": 0,
                                "max": 10
                            },
                            {
                                "id": 2,
                                "color": "blue",
                                "score": 0,
                                "min": 0,
                                "max": 10
                            },
                            {
                                "id": 3,
                                "color": "blueviolet",
                                "score": 0,
                                "min": 0,
                                "max": 10
                            }
                        ]
                    },
                    "TextArea#slider-info": {
                        "text": "TEMPLATE_SLIDER_INFO",
                        "_styles": ""
                    }
                }
            }
        }
    },
    "&explanation_of_items": {
        "_useDefaultNextButton": true,
        "_nextPageConditions": [],
        "_helpTexts": {},
        "components": {
            "TextArea#top": {
                "text": "TEMPLATE_TEXT",
                "_styles": ""
            },
            "TextArea#description": {
                "text": "TEMPLATE_TEXT",
                "_styles": ""
            },
            "Horizontal#1": {
                "Picture#examplepic": {
                    "src": {
                        "path_key": "assets",
                        "filename": "logo.png"
                    },
                    "_styles": "w-52"
                },
                "Vertical#1": {
                    "Horizontal#0": {
                        "Picture#item0": {
                            "src": {
                                "path_key": "assets",
                                "filename": "logo.png"
                            }
                        },
                        "TextArea#item0desc": {
                            "text": "TEMPLATE_TEXT"
                        }
                    },
                    "Horizontal#2": {
                        "Horizontal#3": {
                            "Picture#item1": {
                                "src": {
                                    "path_key": "assets",
                                    "filename": "logo.png"
                                }
                            },
                            "TextArea#item1desc": {
                                "text": "TEMPLATE_TEXT"
                            }
                        },
                        "Horizontal#5": {
                            "Picture#item1": {
                                "src": {
                                    "path_key": "assets",
                                    "filename": "logo.png"
                                }
                            },
                            "TextArea#item1desc": {
                                "text": "TEMPLATE_TEXT"
                            }
                        }
                    },
                    "Horizontal#4": {
                        "Picture#item3": {
                            "src": {
                                "path_key": "assets",
                                "filename": "logo.png"
                            }
                        },
                        "TextArea#item1desc": {
                            "text": "TEMPLATE_TEXT"
                        }
                    }
                }
            }
        }
    }
}